README.md
setup.py
sunidhi/__init__.py
sunidhi/__main__.py
sunidhi.egg-info/PKG-INFO
sunidhi.egg-info/SOURCES.txt
sunidhi.egg-info/dependency_links.txt
sunidhi.egg-info/entry_points.txt
sunidhi.egg-info/requires.txt
sunidhi.egg-info/top_level.txt