Metadata-Version: 2.1
Name: sunidhi
Version: 0.0.5
Summary: Make graph from google sheets
Home-page: UNKNOWN
Author: Sunidhi Batra
Author-email: sunidhibatra08@gmail.com
License: MIT
Keywords: chart
Platform: UNKNOWN
Classifier: Development Status :: 5 - Production/Stable
Classifier: Intended Audience :: Education
Classifier: Operating System :: Microsoft :: Windows :: Windows 10
Classifier: License :: OSI Approved :: MIT License
Classifier: Programming Language :: Python :: 3
